fm_weck/__init__.py
fm_weck/__main__.py
fm_weck/cache_mgr.py
fm_weck/capture.py
fm_weck/cli.py
fm_weck/config.py
fm_weck/engine.py
fm_weck/exceptions.py
fm_weck/file_util.py
fm_weck/image_mgr.py
fm_weck/run_result.py
fm_weck/runexec_mode.py
fm_weck/runexec_util.py
fm_weck/serve.py
fm_weck/smoke_test_mode.py
fm_weck/tmp_file.py
fm_weck/version_listing.py
fm_weck/grpc_service/__init__.py
fm_weck/grpc_service/fm_weck_client.py
fm_weck/grpc_service/fm_weck_server.py
fm_weck/grpc_service/request_handling.py
fm_weck/grpc_service/run_store.py
fm_weck/grpc_service/server_utils.py
fm_weck/grpc_service/proto/__init__.py
fm_weck/grpc_service/proto/fm_weck_service.proto
fm_weck/grpc_service/proto/fm_weck_service_pb2.py
fm_weck/grpc_service/proto/fm_weck_service_pb2.pyi
fm_weck/grpc_service/proto/fm_weck_service_pb2_grpc.py
fm_weck/grpc_service/proto/generate_protocol_files.sh
fm_weck/resources/BenchExec-3.27-py3-none-any.whl
fm_weck/resources/BenchExec-3.27-py3-none-any.whl.license
fm_weck/resources/Containerfile
fm_weck/resources/__init__.py
fm_weck/resources/c_program_example.c
fm_weck/resources/run_with_overlay.sh
fm_weck/resources/runexec
fm_weck/resources/properties/coverage-branches.prp
fm_weck/resources/properties/coverage-branches.prp.license
fm_weck/resources/properties/coverage-conditions.prp
fm_weck/resources/properties/coverage-conditions.prp.license
fm_weck/resources/properties/coverage-error-call.prp
fm_weck/resources/properties/coverage-error-call.prp.license
fm_weck/resources/properties/coverage-statements.prp
fm_weck/resources/properties/coverage-statements.prp.license
fm_weck/resources/properties/def-behavior.prp
fm_weck/resources/properties/def-behavior.prp.license
fm_weck/resources/properties/no-data-race.prp
fm_weck/resources/properties/no-data-race.prp.license
fm_weck/resources/properties/no-overflow.prp
fm_weck/resources/properties/no-overflow.prp.license
fm_weck/resources/properties/termination.prp
fm_weck/resources/properties/termination.prp.license
fm_weck-1.5.3.dist-info/METADATA
fm_weck-1.5.3.dist-info/WHEEL
fm_weck-1.5.3.dist-info/entry_points.txt
fm_weck-1.5.3.dist-info/RECORD
