Metadata-Version: 2.4
Name: fm-weck
Version: 1.5.3
Author-email: Henrik Wachowitz <henrik.wachowitz@ifi.lmu.de>
Maintainer-email: Henrik Wachowitz <henrik.wachowitz@ifi.lmu.de>
Classifier: Development Status :: 4 - Beta
Classifier: Intended Audience :: Developers
Classifier: License :: OSI Approved :: MIT License
Classifier: Programming Language :: Python :: 3.10
Classifier: Programming Language :: Python :: 3.11
Classifier: Programming Language :: Python :: 3.12
Requires-Python: >=3.10
Requires-Dist: argcomplete
Requires-Dist: fm-tools>=1.0.0
Requires-Dist: pyyaml>=6.0
Requires-Dist: tabulate
Requires-Dist: tomli>=2.0; python_version <= '3.10'
Requires-Dist: yaspin>=3.0
Provides-Extra: remote
Requires-Dist: grpcio-tools; extra == 'remote'
